system.cpython-311.pyc (Python 3.11)
[Code]
    File Name: /home/cdctserver/BEAR-HUB/BEAR-HUB/bearhub_rx/bearhub/core/system.py
    Object Name: <module>
    Qualified Name: <module>
    Arg Count: 0
    Pos Only Arg Count: 0
    KW Only Arg Count: 0
    Stack Size: 3
    Flags: 0x01000000 (CO_FUTURE_ANNOTATIONS)
    [Names]
        '__doc__'
        '__future__'
        'annotations'
        'os'
        'pathlib'
        're'
        'shutil'
        'subprocess'
        'Path'
        'home'
        'APP_STATE_DIR'
        '_bactopia_version_cache'
        '__annotations__'
        '_CONFIG_DIR'
        '_LEGACY_CONFIG'
        'which'
        'get_nextflow_bin'
        'nextflow_available'
        'get_bactopia_version'
        'docker_available'
        'get_default_outdir'
        'bootstrap_env'
    [Locals+Names]
    [Constants]
        '\nSystem / environment detection (self-contained, no Streamlit/Reflex deps).\n\nResolves the Nextflow binary and bootstraps BEAR-HUB env vars from the same\nconfig files the legacy launcher uses, so the Reflex app works with an existing\ninstall_bear.sh setup unchanged.\n'
        0
        (
            'annotations'
        )
        None
        '.bactopia_ui_local'
        'str | None'
        '_bactopia_version_cache'
        '.bear-hub'
        'BEAR-HUB'
        '.bear-hub.env'
        'cmd'
        'str'
        'return'
        [Code]
            File Name: /home/cdctserver/BEAR-HUB/BEAR-HUB/bearhub_rx/bearhub/core/system.py
            Object Name: which
            Qualified Name: which
            Arg Count: 1
            Pos Only Arg Count: 0
            KW Only Arg Count: 0
            Stack Size: 3
            Flags: 0x01000003 (CO_OPTIMIZED | CO_NEWLOCALS | CO_FUTURE_ANNOTATIONS)
            [Names]
                'shutil'
                'which'
            [Locals+Names]
                'cmd'
            [Constants]
                None
            [Disassembly]
                0       RESUME                          0
                2       LOAD_GLOBAL                     1: NULL + shutil
                14      LOAD_ATTR                       1: which
                24      LOAD_FAST                       0: cmd
                26      PRECALL                         1
                30      CALL                            1
                40      RETURN_VALUE                    
            [Exception Table]
        [Code]
            File Name: /home/cdctserver/BEAR-HUB/BEAR-HUB/bearhub_rx/bearhub/core/system.py
            Object Name: get_nextflow_bin
            Qualified Name: get_nextflow_bin
            Arg Count: 0
            Pos Only Arg Count: 0
            KW Only Arg Count: 0
            Stack Size: 4
            Flags: 0x01000003 (CO_OPTIMIZED | CO_NEWLOCALS | CO_FUTURE_ANNOTATIONS)
            [Names]
                'os'
                'environ'
                'get'
                'strip'
                'pathlib'
                'Path'
                'expanduser'
                'resolve'
                'is_file'
                'access'
                'X_OK'
                'str'
            [Locals+Names]
                'v'
                'prefix'
                'cand'
            [Constants]
                'Resolve the Nextflow binary (env var → bactopia env prefix → PATH).'
                'NEXTFLOW_BIN'
                ''
                'BACTOPIA_ENV_PREFIX'
                'bin'
                'nextflow'
            [Disassembly]
                0       RESUME                          0
                2       LOAD_GLOBAL                     0: os
                14      LOAD_ATTR                       1: environ
                24      LOAD_METHOD                     2: get
                46      LOAD_CONST                      1: 'NEXTFLOW_BIN'
                48      PRECALL                         1
                52      CALL                            1
                62      JUMP_IF_TRUE_OR_POP             1 (to 2)
                64      LOAD_CONST                      2: ''
                66      LOAD_METHOD                     3: strip
                88      PRECALL                         0
                92      CALL                            0
                102     STORE_FAST                      0: v
                104     LOAD_FAST                       0: v
                106     POP_JUMP_FORWARD_IF_FALSE       2 (to 112)
                108     LOAD_FAST                       0: v
                110     RETURN_VALUE                    
                112     LOAD_GLOBAL                     0: os
                124     LOAD_ATTR                       1: environ
                134     LOAD_METHOD                     2: get
                156     LOAD_CONST                      3: 'BACTOPIA_ENV_PREFIX'
                158     PRECALL                         1
                162     CALL                            1
                172     STORE_FAST                      1: prefix
                174     LOAD_FAST                       1: prefix
                176     POP_JUMP_FORWARD_IF_FALSE       128 (to 434)
                178     LOAD_GLOBAL                     9: NULL + pathlib
                190     LOAD_ATTR                       5: Path
                200     LOAD_FAST                       1: prefix
                202     PRECALL                         1
                206     CALL                            1
                216     LOAD_METHOD                     6: expanduser
                238     PRECALL                         0
                242     CALL                            0
                252     LOAD_METHOD                     7: resolve
                274     PRECALL                         0
                278     CALL                            0
                288     LOAD_CONST                      4: 'bin'
                290     BINARY_OP                       11 (/)
                294     LOAD_CONST                      5: 'nextflow'
                296     BINARY_OP                       11 (/)
                300     STORE_FAST                      2: cand
                302     LOAD_FAST                       2: cand
                304     LOAD_METHOD                     8: is_file
                326     PRECALL                         0
                330     CALL                            0
                340     POP_JUMP_FORWARD_IF_FALSE       46 (to 434)
                342     LOAD_GLOBAL                     1: NULL + os
                354     LOAD_ATTR                       9: access
                364     LOAD_FAST                       2: cand
                366     LOAD_GLOBAL                     0: os
                378     LOAD_ATTR                       10: X_OK
                388     PRECALL                         2
                392     CALL                            2
                402     POP_JUMP_FORWARD_IF_FALSE       15 (to 434)
                404     LOAD_GLOBAL                     23: NULL + str
                416     LOAD_FAST                       2: cand
                418     PRECALL                         1
                422     CALL                            1
                432     RETURN_VALUE                    
                434     LOAD_CONST                      5: 'nextflow'
                436     RETURN_VALUE                    
            [Exception Table]
        'bool'
        [Code]
            File Name: /home/cdctserver/BEAR-HUB/BEAR-HUB/bearhub_rx/bearhub/core/system.py
            Object Name: nextflow_available
            Qualified Name: nextflow_available
            Arg Count: 0
            Pos Only Arg Count: 0
            KW Only Arg Count: 0
            Stack Size: 3
            Flags: 0x01000003 (CO_OPTIMIZED | CO_NEWLOCALS | CO_FUTURE_ANNOTATIONS)
            [Names]
                'get_nextflow_bin'
                'which'
            [Locals+Names]
                'nf'
            [Constants]
                None
                'nextflow'
                True
            [Disassembly]
                0       RESUME                          0
                2       LOAD_GLOBAL                     1: NULL + get_nextflow_bin
                14      PRECALL                         0
                18      CALL                            0
                28      STORE_FAST                      0: nf
                30      LOAD_FAST                       0: nf
                32      LOAD_CONST                      1: 'nextflow'
                34      COMPARE_OP                      3 (!=)
                40      POP_JUMP_FORWARD_IF_FALSE       2 (to 46)
                42      LOAD_CONST                      2: True
                44      JUMP_FORWARD                    16 (to 78)
                46      LOAD_GLOBAL                     3: NULL + which
                58      LOAD_CONST                      1: 'nextflow'
                60      PRECALL                         1
                64      CALL                            1
                74      LOAD_CONST                      0: None
                76      IS_OP                           1 (is not)
                78      RETURN_VALUE                    
            [Exception Table]
        [Code]
            File Name: /home/cdctserver/BEAR-HUB/BEAR-HUB/bearhub_rx/bearhub/core/system.py
            Object Name: get_bactopia_version
            Qualified Name: get_bactopia_version
            Arg Count: 0
            Pos Only Arg Count: 0
            KW Only Arg Count: 0
            Stack Size: 8
            Flags: 0x01000003 (CO_OPTIMIZED | CO_NEWLOCALS | CO_FUTURE_ANNOTATIONS)
            [Names]
                '_bactopia_version_cache'
                'get_nextflow_bin'
                'append'
                'str'
                'pathlib'
                'Path'
                'parent'
                'subprocess'
                'run'
                're'
                'search'
                'stdout'
                'stderr'
                'group'
                'OSError'
                'SubprocessError'
                'os'
                'environ'
                'get'
                'strip'
            [Locals+Names]
                'version'
                'nf'
                'candidates'
                'exe'
                'r'
                'm'
            [Constants]
                "\n    Installed Bactopia version (e.g. '3.2.0'), used to pin `-r v<version>` so\n    Nextflow runs the pipeline revision that matches the env's Nextflow instead\n    of pulling the GitHub default (which may need a newer Nextflow).\n\n    The actual binary is authoritative — the BACTOPIA_VERSION env var only seeds\n    the pinned install default and may differ from what's really installed.\n    "
                None
                ''
                'nextflow'
                'bactopia'
                '--version'
                True
                15
                False
                (
                    'capture_output'
                    'text'
                    'timeout'
                    'check'
                )
                '([0-9]+\\.[0-9]+\\.[0-9]+)'
                1
                'BACTOPIA_VERSION'
            [Disassembly]
                0       RESUME                          0
                2       LOAD_GLOBAL                     0: _bactopia_version_cache
                14      POP_JUMP_FORWARD_IF_NONE        7 (to 30)
                16      LOAD_GLOBAL                     0: _bactopia_version_cache
                28      RETURN_VALUE                    
                30      LOAD_CONST                      2: ''
                32      STORE_FAST                      0: version
                34      LOAD_GLOBAL                     3: NULL + get_nextflow_bin
                46      PRECALL                         0
                50      CALL                            0
                60      STORE_FAST                      1: nf
                62      BUILD_LIST                      0
                64      STORE_FAST                      2: candidates
                66      LOAD_FAST                       1: nf
                68      POP_JUMP_FORWARD_IF_FALSE       66 (to 202)
                70      LOAD_FAST                       1: nf
                72      LOAD_CONST                      3: 'nextflow'
                74      COMPARE_OP                      3 (!=)
                80      POP_JUMP_FORWARD_IF_FALSE       60 (to 202)
                82      LOAD_FAST                       2: candidates
                84      LOAD_METHOD                     2: append
                106     LOAD_GLOBAL                     7: NULL + str
                118     LOAD_GLOBAL                     9: NULL + pathlib
                130     LOAD_ATTR                       5: Path
                140     LOAD_FAST                       1: nf
                142     PRECALL                         1
                146     CALL                            1
                156     LOAD_ATTR                       6: parent
                166     LOAD_CONST                      4: 'bactopia'
                168     BINARY_OP                       11 (/)
                172     PRECALL                         1
                176     CALL                            1
                186     PRECALL                         1
                190     CALL                            1
                200     POP_TOP                         
                202     LOAD_FAST                       2: candidates
                204     LOAD_METHOD                     2: append
                226     LOAD_CONST                      4: 'bactopia'
                228     PRECALL                         1
                232     CALL                            1
                242     POP_TOP                         
                244     LOAD_FAST                       2: candidates
                246     GET_ITER                        
                248     FOR_ITER                        121 (to 492)
                250     STORE_FAST                      3: exe
                252     NOP                             
                254     LOAD_GLOBAL                     15: NULL + subprocess
                266     LOAD_ATTR                       8: run
                276     LOAD_FAST                       3: exe
                278     LOAD_CONST                      5: '--version'
                280     BUILD_LIST                      2
                282     LOAD_CONST                      6: True
                284     LOAD_CONST                      6: True
                286     LOAD_CONST                      7: 15
                288     LOAD_CONST                      8: False
                290     KW_NAMES                        9: ('capture_output', 'text', 'timeout', 'check')
                292     PRECALL                         5
                296     CALL                            5
                306     STORE_FAST                      4: r
                308     LOAD_GLOBAL                     19: NULL + re
                320     LOAD_ATTR                       10: search
                330     LOAD_CONST                      10: '([0-9]+\\.[0-9]+\\.[0-9]+)'
                332     LOAD_FAST                       4: r
                334     LOAD_ATTR                       11: stdout
                344     JUMP_IF_TRUE_OR_POP             1 (to 2)
                346     LOAD_CONST                      2: ''
                348     LOAD_FAST                       4: r
                350     LOAD_ATTR                       12: stderr
                360     JUMP_IF_TRUE_OR_POP             1 (to 2)
                362     LOAD_CONST                      2: ''
                364     BINARY_OP                       0 (+)
                368     PRECALL                         2
                372     CALL                            2
                382     STORE_FAST                      5: m
                384     LOAD_FAST                       5: m
                386     POP_JUMP_FORWARD_IF_FALSE       23 (to 434)
                388     LOAD_FAST                       5: m
                390     LOAD_METHOD                     13: group
                412     LOAD_CONST                      11: 1
                414     PRECALL                         1
                418     CALL                            1
                428     STORE_FAST                      0: version
                430     POP_TOP                         
                432     JUMP_FORWARD                    29 (to 492)
                434     JUMP_BACKWARD                   94 (to 248)
                436     PUSH_EXC_INFO                   
                438     LOAD_GLOBAL                     28: OSError
                450     LOAD_GLOBAL                     14: subprocess
                462     LOAD_ATTR                       15: SubprocessError
                472     BUILD_TUPLE                     2
                474     CHECK_EXC_MATCH                 
                476     POP_JUMP_FORWARD_IF_FALSE       3 (to 484)
                478     POP_TOP                         
                480     POP_EXCEPT                      
                482     JUMP_BACKWARD                   118 (to 248)
                484     RERAISE                         0
                486     COPY                            3
                488     POP_EXCEPT                      
                490     RERAISE                         1
                492     LOAD_FAST                       0: version
                494     POP_JUMP_FORWARD_IF_TRUE        51 (to 598)
                496     LOAD_GLOBAL                     32: os
                508     LOAD_ATTR                       17: environ
                518     LOAD_METHOD                     18: get
                540     LOAD_CONST                      12: 'BACTOPIA_VERSION'
                542     PRECALL                         1
                546     CALL                            1
                556     JUMP_IF_TRUE_OR_POP             1 (to 2)
                558     LOAD_CONST                      2: ''
                560     LOAD_METHOD                     19: strip
                582     PRECALL                         0
                586     CALL                            0
                596     STORE_FAST                      0: version
                598     LOAD_FAST                       0: version
                600     STORE_GLOBAL                    0: _bactopia_version_cache
                602     LOAD_FAST                       0: version
                604     RETURN_VALUE                    
            [Exception Table]
                254 to 430 -> 436 [1] 
                436 to 480 -> 486 [2] lasti
                484 to 486 -> 486 [2] lasti
        [Code]
            File Name: /home/cdctserver/BEAR-HUB/BEAR-HUB/bearhub_rx/bearhub/core/system.py
            Object Name: docker_available
            Qualified Name: docker_available
            Arg Count: 0
            Pos Only Arg Count: 0
            KW Only Arg Count: 0
            Stack Size: 3
            Flags: 0x01000003 (CO_OPTIMIZED | CO_NEWLOCALS | CO_FUTURE_ANNOTATIONS)
            [Names]
                'which'
            [Locals+Names]
            [Constants]
                None
                'docker'
            [Disassembly]
                0       RESUME                          0
                2       LOAD_GLOBAL                     1: NULL + which
                14      LOAD_CONST                      1: 'docker'
                16      PRECALL                         1
                20      CALL                            1
                30      LOAD_CONST                      0: None
                32      IS_OP                           1 (is not)
                34      RETURN_VALUE                    
            [Exception Table]
        [Code]
            File Name: /home/cdctserver/BEAR-HUB/BEAR-HUB/bearhub_rx/bearhub/core/system.py
            Object Name: get_default_outdir
            Qualified Name: get_default_outdir
            Arg Count: 0
            Pos Only Arg Count: 0
            KW Only Arg Count: 0
            Stack Size: 5
            Flags: 0x01000003 (CO_OPTIMIZED | CO_NEWLOCALS | CO_FUTURE_ANNOTATIONS)
            [Names]
                'os'
                'getenv'
                'str'
                'pathlib'
                'Path'
                'expanduser'
                'resolve'
                'home'
            [Locals+Names]
                'env_out'
                'base'
            [Constants]
                None
                'BEAR_HUB_OUTDIR'
                'BEAR_HUB_BASEDIR'
                'bactopia_out'
                'BEAR_DATA'
            [Disassembly]
                0       RESUME                          0
                2       LOAD_GLOBAL                     1: NULL + os
                14      LOAD_ATTR                       1: getenv
                24      LOAD_CONST                      1: 'BEAR_HUB_OUTDIR'
                26      PRECALL                         1
                30      CALL                            1
                40      STORE_FAST                      0: env_out
                42      LOAD_FAST                       0: env_out
                44      POP_JUMP_FORWARD_IF_FALSE       69 (to 184)
                46      LOAD_GLOBAL                     5: NULL + str
                58      LOAD_GLOBAL                     7: NULL + pathlib
                70      LOAD_ATTR                       4: Path
                80      LOAD_FAST                       0: env_out
                82      PRECALL                         1
                86      CALL                            1
                96      LOAD_METHOD                     5: expanduser
                118     PRECALL                         0
                122     CALL                            0
                132     LOAD_METHOD                     6: resolve
                154     PRECALL                         0
                158     CALL                            0
                168     PRECALL                         1
                172     CALL                            1
                182     RETURN_VALUE                    
                184     LOAD_GLOBAL                     1: NULL + os
                196     LOAD_ATTR                       1: getenv
                206     LOAD_CONST                      2: 'BEAR_HUB_BASEDIR'
                208     PRECALL                         1
                212     CALL                            1
                222     STORE_FAST                      1: base
                224     LOAD_FAST                       1: base
                226     POP_JUMP_FORWARD_IF_FALSE       72 (to 372)
                228     LOAD_GLOBAL                     5: NULL + str
                240     LOAD_GLOBAL                     7: NULL + pathlib
                252     LOAD_ATTR                       4: Path
                262     LOAD_FAST                       1: base
                264     PRECALL                         1
                268     CALL                            1
                278     LOAD_METHOD                     5: expanduser
                300     PRECALL                         0
                304     CALL                            0
                314     LOAD_CONST                      3: 'bactopia_out'
                316     BINARY_OP                       11 (/)
                320     LOAD_METHOD                     6: resolve
                342     PRECALL                         0
                346     CALL                            0
                356     PRECALL                         1
                360     CALL                            1
                370     RETURN_VALUE                    
                372     LOAD_GLOBAL                     5: NULL + str
                384     LOAD_GLOBAL                     6: pathlib
                396     LOAD_ATTR                       4: Path
                406     LOAD_METHOD                     7: home
                428     PRECALL                         0
                432     CALL                            0
                442     LOAD_CONST                      4: 'BEAR_DATA'
                444     BINARY_OP                       11 (/)
                448     LOAD_CONST                      3: 'bactopia_out'
                450     BINARY_OP                       11 (/)
                454     LOAD_METHOD                     6: resolve
                476     PRECALL                         0
                480     CALL                            0
                490     PRECALL                         1
                494     CALL                            1
                504     RETURN_VALUE                    
            [Exception Table]
        'None'
        [Code]
            File Name: /home/cdctserver/BEAR-HUB/BEAR-HUB/bearhub_rx/bearhub/core/system.py
            Object Name: bootstrap_env
            Qualified Name: bootstrap_env
            Arg Count: 0
            Pos Only Arg Count: 0
            KW Only Arg Count: 0
            Stack Size: 6
            Flags: 0x01000003 (CO_OPTIMIZED | CO_NEWLOCALS | CO_FUTURE_ANNOTATIONS)
            [Names]
                'os'
                'environ'
                'get'
                '_CONFIG_DIR'
                'append'
                'pathlib'
                'Path'
                'expanduser'
                '_LEGACY_CONFIG'
                'is_file'
                'read_text'
                'splitlines'
                'strip'
                'startswith'
                're'
                'match'
                'group'
                'OSError'
            [Locals+Names]
                'candidates'
                'root'
                'cfg'
                'line'
                'm'
                'var'
                'value'
            [Constants]
                'Load env vars from the BEAR-HUB config file, if present.'
                'BACTOPIA_ENV_PREFIX'
                'NXF_CONDA_EXE'
                None
                'config.env'
                'BEAR_HUB_ROOT'
                '.bear-hub.env'
                'utf-8'
                (
                    'encoding'
                )
                '#'
                'export\\s+([A-Za-z_][A-Za-z0-9_]*)=(.*)'
                1
                2
                -1
                frozenset({
                    '"'
                    "'"
                })
                'BEAR_HUB_BASEDIR'
            [Disassembly]
                0       RESUME                          0
                2       LOAD_GLOBAL                     0: os
                14      LOAD_ATTR                       1: environ
                24      LOAD_METHOD                     2: get
                46      LOAD_CONST                      1: 'BACTOPIA_ENV_PREFIX'
                48      PRECALL                         1
                52      CALL                            1
                62      POP_JUMP_FORWARD_IF_FALSE       33 (to 130)
                64      LOAD_GLOBAL                     0: os
                76      LOAD_ATTR                       1: environ
                86      LOAD_METHOD                     2: get
                108     LOAD_CONST                      2: 'NXF_CONDA_EXE'
                110     PRECALL                         1
                114     CALL                            1
                124     POP_JUMP_FORWARD_IF_FALSE       2 (to 130)
                126     LOAD_CONST                      3: None
                128     RETURN_VALUE                    
                130     LOAD_GLOBAL                     6: _CONFIG_DIR
                142     LOAD_CONST                      4: 'config.env'
                144     BINARY_OP                       11 (/)
                148     BUILD_LIST                      1
                150     STORE_FAST                      0: candidates
                152     LOAD_GLOBAL                     0: os
                164     LOAD_ATTR                       1: environ
                174     LOAD_METHOD                     2: get
                196     LOAD_CONST                      5: 'BEAR_HUB_ROOT'
                198     PRECALL                         1
                202     CALL                            1
                212     STORE_FAST                      1: root
                214     LOAD_FAST                       1: root
                216     POP_JUMP_FORWARD_IF_FALSE       60 (to 338)
                218     LOAD_FAST                       0: candidates
                220     LOAD_METHOD                     4: append
                242     LOAD_GLOBAL                     11: NULL + pathlib
                254     LOAD_ATTR                       6: Path
                264     LOAD_FAST                       1: root
                266     PRECALL                         1
                270     CALL                            1
                280     LOAD_METHOD                     7: expanduser
                302     PRECALL                         0
                306     CALL                            0
                316     LOAD_CONST                      6: '.bear-hub.env'
                318     BINARY_OP                       11 (/)
                322     PRECALL                         1
                326     CALL                            1
                336     POP_TOP                         
                338     LOAD_FAST                       0: candidates
                340     LOAD_METHOD                     4: append
                362     LOAD_GLOBAL                     16: _LEGACY_CONFIG
                374     PRECALL                         1
                378     CALL                            1
                388     POP_TOP                         
                390     LOAD_FAST                       0: candidates
                392     GET_ITER                        
                394     FOR_ITER                        290 (to 978)
                398     STORE_FAST                      2: cfg
                400     NOP                             
                402     LOAD_FAST                       2: cfg
                404     LOAD_METHOD                     9: is_file
                426     PRECALL                         0
                430     CALL                            0
                440     POP_JUMP_FORWARD_IF_TRUE        1 (to 444)
                442     JUMP_BACKWARD                   25 (to 394)
                444     LOAD_FAST                       2: cfg
                446     LOAD_METHOD                     10: read_text
                468     LOAD_CONST                      7: 'utf-8'
                470     KW_NAMES                        8: ('encoding',)
                472     PRECALL                         1
                476     CALL                            1
                486     LOAD_METHOD                     11: splitlines
                508     PRECALL                         0
                512     CALL                            0
                522     GET_ITER                        
                524     FOR_ITER                        207 (to 940)
                526     STORE_FAST                      3: line
                528     LOAD_FAST                       3: line
                530     LOAD_METHOD                     12: strip
                552     PRECALL                         0
                556     CALL                            0
                566     STORE_FAST                      3: line
                568     LOAD_FAST                       3: line
                570     POP_JUMP_FORWARD_IF_FALSE       21 (to 614)
                572     LOAD_FAST                       3: line
                574     LOAD_METHOD                     13: startswith
                596     LOAD_CONST                      9: '#'
                598     PRECALL                         1
                602     CALL                            1
                612     POP_JUMP_FORWARD_IF_FALSE       1 (to 616)
                614     JUMP_BACKWARD                   46 (to 524)
                616     LOAD_GLOBAL                     29: NULL + re
                628     LOAD_ATTR                       15: match
                638     LOAD_CONST                      10: 'export\\s+([A-Za-z_][A-Za-z0-9_]*)=(.*)'
                640     LOAD_FAST                       3: line
                642     PRECALL                         2
                646     CALL                            2
                656     STORE_FAST                      4: m
                658     LOAD_FAST                       4: m
                660     POP_JUMP_FORWARD_IF_TRUE        1 (to 664)
                662     JUMP_BACKWARD                   70 (to 524)
                664     LOAD_FAST                       4: m
                666     LOAD_METHOD                     16: group
                688     LOAD_CONST                      11: 1
                690     PRECALL                         1
                694     CALL                            1
                704     LOAD_FAST                       4: m
                706     LOAD_METHOD                     16: group
                728     LOAD_CONST                      12: 2
                730     PRECALL                         1
                734     CALL                            1
                744     LOAD_METHOD                     12: strip
                766     PRECALL                         0
                770     CALL                            0
                780     STORE_FAST                      6: value
                782     STORE_FAST                      5: var
                784     LOAD_FAST                       6: value
                786     LOAD_CONST                      3: None
                788     LOAD_CONST                      11: 1
                790     BUILD_SLICE                     2
                792     BINARY_SUBSCR                   
                802     LOAD_FAST                       6: value
                804     LOAD_CONST                      13: -1
                806     LOAD_CONST                      3: None
                808     BUILD_SLICE                     2
                810     BINARY_SUBSCR                   
                820     COMPARE_OP                      2 (==)
                826     POP_JUMP_FORWARD_IF_FALSE       22 (to 872)
                828     LOAD_FAST                       6: value
                830     LOAD_CONST                      3: None
                832     LOAD_CONST                      11: 1
                834     BUILD_SLICE                     2
                836     BINARY_SUBSCR                   
                846     LOAD_CONST                      14: frozenset({'"', "'"})
                848     CONTAINS_OP                     0 (in)
                850     POP_JUMP_FORWARD_IF_FALSE       10 (to 872)
                852     LOAD_FAST                       6: value
                854     LOAD_CONST                      11: 1
                856     LOAD_CONST                      13: -1
                858     BUILD_SLICE                     2
                860     BINARY_SUBSCR                   
                870     STORE_FAST                      6: value
                872     LOAD_FAST                       5: var
                874     POP_JUMP_FORWARD_IF_FALSE       31 (to 938)
                876     LOAD_FAST                       6: value
                878     POP_JUMP_FORWARD_IF_FALSE       29 (to 938)
                880     LOAD_FAST                       5: var
                882     LOAD_GLOBAL                     0: os
                894     LOAD_ATTR                       1: environ
                904     CONTAINS_OP                     1 (not in)
                906     POP_JUMP_FORWARD_IF_FALSE       15 (to 938)
                908     LOAD_FAST                       6: value
                910     LOAD_GLOBAL                     0: os
                922     LOAD_ATTR                       1: environ
                932     LOAD_FAST                       5: var
                934     STORE_SUBSCR                    
                938     JUMP_BACKWARD                   208 (to 524)
                940     POP_TOP                         
                942     JUMP_FORWARD                    17 (to 978)
                944     PUSH_EXC_INFO                   
                946     LOAD_GLOBAL                     34: OSError
                958     CHECK_EXC_MATCH                 
                960     POP_JUMP_FORWARD_IF_FALSE       4 (to 970)
                962     POP_TOP                         
                964     POP_EXCEPT                      
                966     JUMP_BACKWARD                   288 (to 394)
                970     RERAISE                         0
                972     COPY                            3
                974     POP_EXCEPT                      
                976     RERAISE                         1
                978     LOAD_GLOBAL                     0: os
                990     LOAD_ATTR                       1: environ
                1000    LOAD_METHOD                     2: get
                1022    LOAD_CONST                      5: 'BEAR_HUB_ROOT'
                1024    PRECALL                         1
                1028    CALL                            1
                1038    POP_JUMP_FORWARD_IF_FALSE       64 (to 1168)
                1040    LOAD_GLOBAL                     0: os
                1052    LOAD_ATTR                       1: environ
                1062    LOAD_METHOD                     2: get
                1084    LOAD_CONST                      15: 'BEAR_HUB_BASEDIR'
                1086    PRECALL                         1
                1090    CALL                            1
                1100    POP_JUMP_FORWARD_IF_TRUE        35 (to 1172)
                1102    LOAD_GLOBAL                     0: os
                1114    LOAD_ATTR                       1: environ
                1124    LOAD_CONST                      5: 'BEAR_HUB_ROOT'
                1126    BINARY_SUBSCR                   
                1136    LOAD_GLOBAL                     0: os
                1148    LOAD_ATTR                       1: environ
                1158    LOAD_CONST                      15: 'BEAR_HUB_BASEDIR'
                1160    STORE_SUBSCR                    
                1164    LOAD_CONST                      3: None
                1166    RETURN_VALUE                    
                1168    LOAD_CONST                      3: None
                1170    RETURN_VALUE                    
                1172    LOAD_CONST                      3: None
                1174    RETURN_VALUE                    
            [Exception Table]
                402 to 442 -> 944 [1] 
                444 to 940 -> 944 [1] 
                944 to 964 -> 972 [2] lasti
                970 to 972 -> 972 [2] lasti
        (
            'cmd'
            'str'
            'return'
            'str | None'
        )
        (
            'return'
            'str'
        )
        (
            'return'
            'bool'
        )
        (
            'return'
            'None'
        )
    [Disassembly]
        0       RESUME                          0
        2       SETUP_ANNOTATIONS               
        4       LOAD_CONST                      0: '\nSystem / environment detection (self-contained, no Streamlit/Reflex deps).\n\nResolves the Nextflow binary and bootstraps BEAR-HUB env vars from the same\nconfig files the legacy launcher uses, so the Reflex app works with an existing\ninstall_bear.sh setup unchanged.\n'
        6       STORE_NAME                      0: __doc__
        8       LOAD_CONST                      1: 0
        10      LOAD_CONST                      2: ('annotations',)
        12      IMPORT_NAME                     1: __future__
        14      IMPORT_FROM                     2: annotations
        16      STORE_NAME                      2: annotations
        18      POP_TOP                         
        20      LOAD_CONST                      1: 0
        22      LOAD_CONST                      3: None
        24      IMPORT_NAME                     3: os
        26      STORE_NAME                      3: os
        28      LOAD_CONST                      1: 0
        30      LOAD_CONST                      3: None
        32      IMPORT_NAME                     4: pathlib
        34      STORE_NAME                      4: pathlib
        36      LOAD_CONST                      1: 0
        38      LOAD_CONST                      3: None
        40      IMPORT_NAME                     5: re
        42      STORE_NAME                      5: re
        44      LOAD_CONST                      1: 0
        46      LOAD_CONST                      3: None
        48      IMPORT_NAME                     6: shutil
        50      STORE_NAME                      6: shutil
        52      LOAD_CONST                      1: 0
        54      LOAD_CONST                      3: None
        56      IMPORT_NAME                     7: subprocess
        58      STORE_NAME                      7: subprocess
        60      LOAD_NAME                       4: pathlib
        62      LOAD_ATTR                       8: Path
        72      LOAD_METHOD                     9: home
        94      PRECALL                         0
        98      CALL                            0
        108     LOAD_CONST                      4: '.bactopia_ui_local'
        110     BINARY_OP                       11 (/)
        114     STORE_NAME                      10: APP_STATE_DIR
        116     LOAD_CONST                      3: None
        118     STORE_GLOBAL                    11: _bactopia_version_cache
        120     LOAD_CONST                      5: 'str | None'
        122     LOAD_NAME                       12: __annotations__
        124     LOAD_CONST                      6: '_bactopia_version_cache'
        126     STORE_SUBSCR                    
        130     LOAD_NAME                       4: pathlib
        132     LOAD_ATTR                       8: Path
        142     LOAD_METHOD                     9: home
        164     PRECALL                         0
        168     CALL                            0
        178     LOAD_CONST                      7: '.bear-hub'
        180     BINARY_OP                       11 (/)
        184     STORE_NAME                      13: _CONFIG_DIR
        186     LOAD_NAME                       4: pathlib
        188     LOAD_ATTR                       8: Path
        198     LOAD_METHOD                     9: home
        220     PRECALL                         0
        224     CALL                            0
        234     LOAD_CONST                      8: 'BEAR-HUB'
        236     BINARY_OP                       11 (/)
        240     LOAD_CONST                      9: '.bear-hub.env'
        242     BINARY_OP                       11 (/)
        246     STORE_NAME                      14: _LEGACY_CONFIG
        248     LOAD_CONST                      22: ('cmd', 'str', 'return', 'str | None')
        250     LOAD_CONST                      13: <CODE> which
        252     MAKE_FUNCTION                   4
        254     STORE_NAME                      15: which
        256     LOAD_CONST                      23: ('return', 'str')
        258     LOAD_CONST                      14: <CODE> get_nextflow_bin
        260     MAKE_FUNCTION                   4
        262     STORE_NAME                      16: get_nextflow_bin
        264     LOAD_CONST                      24: ('return', 'bool')
        266     LOAD_CONST                      16: <CODE> nextflow_available
        268     MAKE_FUNCTION                   4
        270     STORE_NAME                      17: nextflow_available
        272     LOAD_CONST                      23: ('return', 'str')
        274     LOAD_CONST                      17: <CODE> get_bactopia_version
        276     MAKE_FUNCTION                   4
        278     STORE_NAME                      18: get_bactopia_version
        280     LOAD_CONST                      24: ('return', 'bool')
        282     LOAD_CONST                      18: <CODE> docker_available
        284     MAKE_FUNCTION                   4
        286     STORE_NAME                      19: docker_available
        288     LOAD_CONST                      23: ('return', 'str')
        290     LOAD_CONST                      19: <CODE> get_default_outdir
        292     MAKE_FUNCTION                   4
        294     STORE_NAME                      20: get_default_outdir
        296     LOAD_CONST                      25: ('return', 'None')
        298     LOAD_CONST                      21: <CODE> bootstrap_env
        300     MAKE_FUNCTION                   4
        302     STORE_NAME                      21: bootstrap_env
        304     LOAD_CONST                      3: None
        306     RETURN_VALUE                    
    [Exception Table]
